ssc_concurrent_log_handler/__init__.py
ssc_concurrent_log_handler/__version__.py
sc_concurrent_log_handler-0.0.14.dist-info/METADATA
sc_concurrent_log_handler-0.0.14.dist-info/WHEEL
sc_concurrent_log_handler-0.0.14.dist-info/top_level.txt
sc_concurrent_log_handler-0.0.14.dist-info/RECORD
