Metadata-Version: 2.1
Name: sc-concurrent-log-handler
Version: 0.0.14
Summary: SSC Enhanced RotatingFileHandler replacement with concurrency, gzip and Windows support
Home-page: UNKNOWN
Author: Aric Yang
Author-email: yangzhao9@baidu.com
License: http://www.apache.org/licenses/LICENSE-2.0
Keywords: logging,windows,linux,unix,rotate,QueueHandler,QueueListener,portalocker
Platform: UNKNOWN
Classifier: Development Status :: 4 - Beta
Classifier: Topic :: System :: Logging
Classifier: Operating System :: POSIX
Classifier: Operating System :: Microsoft :: Windows
Classifier: Programming Language :: Python
Classifier: Programming Language :: Python :: 3
Classifier: Programming Language :: Python :: 3.6
Classifier: Programming Language :: Python :: 3.7
Classifier: Programming Language :: Python :: 3.8
Classifier: Programming Language :: Python :: 3.9
Classifier: Programming Language :: Python :: 3.10
Classifier: Programming Language :: Python :: 3.11
Classifier: Programming Language :: Python :: 3.12
Classifier: Topic :: Software Development :: Libraries :: Python Modules
Classifier: License :: OSI Approved :: Apache Software License
Requires-Python: >=3.6
Requires-Dist: portalocker (>=1.6.0)
Requires-Dist: concurrent-log-handler (>=0.9.24)
Provides-Extra: dev
Requires-Dist: pytest ; extra == 'dev'
Requires-Dist: tox ; extra == 'dev'
Requires-Dist: black ; extra == 'dev'
Requires-Dist: ruff ; extra == 'dev'
Requires-Dist: concurrent-log-handler ; extra == 'dev'
